{
  "annotations": {
    "list": []
  },
  "description": "Comprehensive user profile view combining PnL, strategy signals, market exposure, and liquidity quality",
  "editable": true,
  "fiscalYearStartMonth": 0,
  "graphTooltip": 1,
  "id": null,
  "links": [
    {
      "asDropdown": true,
      "icon": "external link",
      "includeVars": true,
      "keepTime": true,
      "tags": ["polyttool"],
      "targetBlank": true,
      "title": "Related Dashboards",
      "tooltip": "",
      "type": "dashboards",
      "url": ""
    }
  ],
  "panels": [
    {
      "collapsed": false,
      "gridPos": {
        "h": 1,
        "w": 24,
        "x": 0,
        "y": 0
      },
      "id": 100,
      "panels": [],
      "title": "User Summary",
      "type": "row"
    },
    {
      "datasource": {
        "type": "grafana-clickhouse-datasource",
        "uid": "clickhouse-polyttool"
      },
      "fieldConfig": {
        "defaults": {
          "color": {
            "mode": "thresholds"
          },
          "mappings": [],
          "thresholds": {
            "mode": "absolute",
            "steps": [
              {
                "color": "blue",
                "value": null
              }
            ]
          }
        },
        "overrides": []
      },
      "gridPos": {
        "h": 3,
        "w": 4,
        "x": 0,
        "y": 1
      },
      "id": 1,
      "options": {
        "colorMode": "value",
        "graphMode": "none",
        "justifyMode": "auto",
        "orientation": "auto",
        "reduceOptions": {
          "calcs": ["lastNotNull"],
          "fields": "",
          "values": false
        },
        "textMode": "auto",
        "wideLayout": true
      },
      "pluginVersion": "11.4.0",
      "targets": [
        {
          "datasource": {
            "type": "grafana-clickhouse-datasource",
            "uid": "clickhouse-polyttool"
          },
          "editorType": "sql",
          "format": 1,
          "queryType": "table",
          "rawSql": "SELECT count(DISTINCT trade_uid) AS total_trades\nFROM polyttool.user_trades\nWHERE proxy_wallet = '$proxy_wallet'",
          "refId": "A"
        }
      ],
      "title": "Total Trades",
      "type": "stat"
    },
    {
      "datasource": {
        "type": "grafana-clickhouse-datasource",
        "uid": "clickhouse-polyttool"
      },
      "fieldConfig": {
        "defaults": {
          "color": {
            "mode": "thresholds"
          },
          "mappings": [],
          "thresholds": {
            "mode": "absolute",
            "steps": [
              {
                "color": "purple",
                "value": null
              }
            ]
          },
          "unit": "currencyUSD"
        },
        "overrides": []
      },
      "gridPos": {
        "h": 3,
        "w": 4,
        "x": 4,
        "y": 1
      },
      "id": 2,
      "options": {
        "colorMode": "value",
        "graphMode": "none",
        "justifyMode": "auto",
        "orientation": "auto",
        "reduceOptions": {
          "calcs": ["lastNotNull"],
          "fields": "",
          "values": false
        },
        "textMode": "auto",
        "wideLayout": true
      },
      "pluginVersion": "11.4.0",
      "targets": [
        {
          "datasource": {
            "type": "grafana-clickhouse-datasource",
            "uid": "clickhouse-polyttool"
          },
          "editorType": "sql",
          "format": 1,
          "queryType": "table",
          "rawSql": "SELECT sum(size * price) AS total_volume\nFROM polyttool.user_trades\nWHERE proxy_wallet = '$proxy_wallet'",
          "refId": "A"
        }
      ],
      "title": "Total Volume",
      "type": "stat"
    },
    {
      "datasource": {
        "type": "grafana-clickhouse-datasource",
        "uid": "clickhouse-polyttool"
      },
      "fieldConfig": {
        "defaults": {
          "color": {
            "mode": "thresholds"
          },
          "mappings": [],
          "thresholds": {
            "mode": "absolute",
            "steps": [
              {
                "color": "green",
                "value": null
              }
            ]
          }
        },
        "overrides": []
      },
      "gridPos": {
        "h": 3,
        "w": 4,
        "x": 8,
        "y": 1
      },
      "id": 3,
      "options": {
        "colorMode": "value",
        "graphMode": "none",
        "justifyMode": "auto",
        "orientation": "auto",
        "reduceOptions": {
          "calcs": ["lastNotNull"],
          "fields": "",
          "values": false
        },
        "textMode": "auto",
        "wideLayout": true
      },
      "pluginVersion": "11.4.0",
      "targets": [
        {
          "datasource": {
            "type": "grafana-clickhouse-datasource",
            "uid": "clickhouse-polyttool"
          },
          "editorType": "sql",
          "format": 1,
          "queryType": "table",
          "rawSql": "SELECT count(DISTINCT condition_id) AS markets\nFROM polyttool.user_trades\nWHERE proxy_wallet = '$proxy_wallet'\n  AND condition_id != ''",
          "refId": "A"
        }
      ],
      "title": "Markets Traded",
      "type": "stat"
    },
    {
      "datasource": {
        "type": "grafana-clickhouse-datasource",
        "uid": "clickhouse-polyttool"
      },
      "fieldConfig": {
        "defaults": {
          "color": {
            "mode": "thresholds"
          },
          "mappings": [],
          "thresholds": {
            "mode": "absolute",
            "steps": [
              {
                "color": "orange",
                "value": null
              }
            ]
          }
        },
        "overrides": []
      },
      "gridPos": {
        "h": 3,
        "w": 4,
        "x": 12,
        "y": 1
      },
      "id": 4,
      "options": {
        "colorMode": "value",
        "graphMode": "none",
        "justifyMode": "auto",
        "orientation": "auto",
        "reduceOptions": {
          "calcs": ["lastNotNull"],
          "fields": "",
          "values": false
        },
        "textMode": "auto",
        "wideLayout": true
      },
      "pluginVersion": "11.4.0",
      "targets": [
        {
          "datasource": {
            "type": "grafana-clickhouse-datasource",
            "uid": "clickhouse-polyttool"
          },
          "editorType": "sql",
          "format": 1,
          "queryType": "table",
          "rawSql": "SELECT dateDiff('day', min(ts), max(ts)) AS active_days\nFROM polyttool.user_trades\nWHERE proxy_wallet = '$proxy_wallet'",
          "refId": "A"
        }
      ],
      "title": "Active Days",
      "type": "stat"
    },
    {
      "datasource": {
        "type": "grafana-clickhouse-datasource",
        "uid": "clickhouse-polyttool"
      },
      "fieldConfig": {
        "defaults": {
          "color": {
            "mode": "thresholds"
          },
          "mappings": [],
          "thresholds": {
            "mode": "absolute",
            "steps": [
              {
                "color": "red",
                "value": null
              },
              {
                "color": "yellow",
                "value": 50
              },
              {
                "color": "green",
                "value": 80
              }
            ]
          },
          "unit": "percent"
        },
        "overrides": []
      },
      "gridPos": {
        "h": 3,
        "w": 4,
        "x": 16,
        "y": 1
      },
      "id": 5,
      "options": {
        "colorMode": "value",
        "graphMode": "none",
        "justifyMode": "auto",
        "orientation": "auto",
        "reduceOptions": {
          "calcs": ["lastNotNull"],
          "fields": "",
          "values": false
        },
        "textMode": "auto",
        "wideLayout": true
      },
      "pluginVersion": "11.4.0",
      "targets": [
        {
          "datasource": {
            "type": "grafana-clickhouse-datasource",
            "uid": "clickhouse-polyttool"
          },
          "editorType": "sql",
          "format": 1,
          "queryType": "table",
          "rawSql": "SELECT\n  countIf(mt.token_id IS NOT NULL) * 100.0 / count() AS mapping_pct\nFROM polyttool.user_trades t\nLEFT JOIN polyttool.market_tokens mt ON t.token_id = mt.token_id\nWHERE t.proxy_wallet = '$proxy_wallet'",
          "refId": "A"
        }
      ],
      "title": "Mapping Coverage",
      "type": "stat"
    },
    {
      "datasource": {
        "type": "grafana-clickhouse-datasource",
        "uid": "clickhouse-polyttool"
      },
      "fieldConfig": {
        "defaults": {
          "color": {
            "mode": "thresholds"
          },
          "mappings": [],
          "thresholds": {
            "mode": "absolute",
            "steps": [
              {
                "color": "green",
                "value": null
              }
            ]
          },
          "unit": "currencyUSD"
        },
        "overrides": []
      },
      "gridPos": {
        "h": 3,
        "w": 4,
        "x": 20,
        "y": 1
      },
      "id": 6,
      "options": {
        "colorMode": "value",
        "graphMode": "none",
        "justifyMode": "auto",
        "orientation": "auto",
        "reduceOptions": {
          "calcs": ["lastNotNull"],
          "fields": "",
          "values": false
        },
        "textMode": "auto",
        "wideLayout": true
      },
      "pluginVersion": "11.4.0",
      "targets": [
        {
          "datasource": {
            "type": "grafana-clickhouse-datasource",
            "uid": "clickhouse-polyttool"
          },
          "editorType": "sql",
          "format": 1,
          "queryType": "table",
          "rawSql": "WITH latest AS (\n  SELECT max(bucket_start) AS b\n  FROM polyttool.user_pnl_bucket\n  WHERE proxy_wallet = '$proxy_wallet' AND bucket_type = '$bucket_type'\n)\nSELECT argMax(realized_pnl, computed_at) AS realized_pnl\nFROM polyttool.user_pnl_bucket\nWHERE proxy_wallet = '$proxy_wallet'\n  AND bucket_type = '$bucket_type'\n  AND bucket_start = (SELECT b FROM latest)",
          "refId": "A"
        }
      ],
      "title": "Latest Realized PnL",
      "type": "stat"
    },
    {
      "collapsed": false,
      "gridPos": {
        "h": 1,
        "w": 24,
        "x": 0,
        "y": 4
      },
      "id": 101,
      "panels": [],
      "title": "PnL & Exposure",
      "type": "row"
    },
    {
      "datasource": {
        "type": "grafana-clickhouse-datasource",
        "uid": "clickhouse-polyttool"
      },
      "fieldConfig": {
        "defaults": {
          "color": {
            "mode": "palette-classic"
          },
          "custom": {
            "axisBorderShow": false,
            "axisCenteredZero": true,
            "axisColorMode": "text",
            "axisLabel": "",
            "axisPlacement": "auto",
            "barAlignment": 0,
            "barWidthFactor": 0.6,
            "drawStyle": "line",
            "fillOpacity": 20,
            "gradientMode": "none",
            "hideFrom": {
              "legend": false,
              "tooltip": false,
              "viz": false
            },
            "insertNulls": false,
            "lineInterpolation": "linear",
            "lineWidth": 2,
            "pointSize": 5,
            "scaleDistribution": {
              "type": "linear"
            },
            "showPoints": "auto",
            "spanNulls": false,
            "stacking": {
              "group": "A",
              "mode": "none"
            },
            "thresholdsStyle": {
              "mode": "off"
            }
          },
          "mappings": [],
          "thresholds": {
            "mode": "absolute",
            "steps": [
              {
                "color": "green",
                "value": null
              }
            ]
          },
          "unit": "currencyUSD"
        },
        "overrides": [
          {
            "matcher": {
              "id": "byName",
              "options": "Realized PnL"
            },
            "properties": [
              {
                "id": "color",
                "value": {
                  "fixedColor": "green",
                  "mode": "fixed"
                }
              }
            ]
          },
          {
            "matcher": {
              "id": "byName",
              "options": "MTM Estimate"
            },
            "properties": [
              {
                "id": "color",
                "value": {
                  "fixedColor": "blue",
                  "mode": "fixed"
                }
              },
              {
                "id": "custom.lineStyle",
                "value": {
                  "dash": [10, 10],
                  "fill": "dash"
                }
              }
            ]
          }
        ]
      },
      "gridPos": {
        "h": 7,
        "w": 12,
        "x": 0,
        "y": 5
      },
      "id": 10,
      "options": {
        "legend": {
          "calcs": ["lastNotNull", "sum"],
          "displayMode": "table",
          "placement": "bottom",
          "showLegend": true
        },
        "tooltip": {
          "mode": "multi",
          "sort": "desc"
        }
      },
      "pluginVersion": "11.4.0",
      "targets": [
        {
          "datasource": {
            "type": "grafana-clickhouse-datasource",
            "uid": "clickhouse-polyttool"
          },
          "editorType": "sql",
          "format": 1,
          "queryType": "timeseries",
          "rawSql": "SELECT\n  bucket_start AS time,\n  argMax(realized_pnl, computed_at) AS \"Realized PnL\",\n  argMax(mtm_pnl_estimate, computed_at) AS \"MTM Estimate\"\nFROM polyttool.user_pnl_bucket\nWHERE proxy_wallet = '$proxy_wallet'\n  AND bucket_type = '$bucket_type'\nGROUP BY bucket_start\nORDER BY time",
          "refId": "A"
        }
      ],
      "title": "PnL Over Time",
      "type": "timeseries"
    },
    {
      "datasource": {
        "type": "grafana-clickhouse-datasource",
        "uid": "clickhouse-polyttool"
      },
      "fieldConfig": {
        "defaults": {
          "color": {
            "mode": "palette-classic"
          },
          "custom": {
            "axisBorderShow": false,
            "axisCenteredZero": false,
            "axisColorMode": "text",
            "axisLabel": "",
            "axisPlacement": "auto",
            "barAlignment": 0,
            "barWidthFactor": 0.6,
            "drawStyle": "line",
            "fillOpacity": 30,
            "gradientMode": "none",
            "hideFrom": {
              "legend": false,
              "tooltip": false,
              "viz": false
            },
            "insertNulls": false,
            "lineInterpolation": "linear",
            "lineWidth": 2,
            "pointSize": 5,
            "scaleDistribution": {
              "type": "linear"
            },
            "showPoints": "auto",
            "spanNulls": false,
            "stacking": {
              "group": "A",
              "mode": "none"
            },
            "thresholdsStyle": {
              "mode": "off"
            }
          },
          "mappings": [],
          "thresholds": {
            "mode": "absolute",
            "steps": [
              {
                "color": "green",
                "value": null
              }
            ]
          },
          "unit": "currencyUSD"
        },
        "overrides": []
      },
      "gridPos": {
        "h": 7,
        "w": 12,
        "x": 12,
        "y": 5
      },
      "id": 11,
      "options": {
        "legend": {
          "calcs": ["lastNotNull", "max"],
          "displayMode": "table",
          "placement": "bottom",
          "showLegend": true
        },
        "tooltip": {
          "mode": "multi",
          "sort": "desc"
        }
      },
      "pluginVersion": "11.4.0",
      "targets": [
        {
          "datasource": {
            "type": "grafana-clickhouse-datasource",
            "uid": "clickhouse-polyttool"
          },
          "editorType": "sql",
          "format": 1,
          "queryType": "timeseries",
          "rawSql": "SELECT\n  bucket_start AS time,\n  argMax(exposure_notional_estimate, computed_at) AS \"Exposure\"\nFROM polyttool.user_pnl_bucket\nWHERE proxy_wallet = '$proxy_wallet'\n  AND bucket_type = '$bucket_type'\nGROUP BY bucket_start\nORDER BY time",
          "refId": "A"
        }
      ],
      "title": "Exposure Over Time",
      "type": "timeseries"
    },
    {
      "collapsed": false,
      "gridPos": {
        "h": 1,
        "w": 24,
        "x": 0,
        "y": 12
      },
      "id": 102,
      "panels": [],
      "title": "Strategy Signals",
      "type": "row"
    },
    {
      "datasource": {
        "type": "grafana-clickhouse-datasource",
        "uid": "clickhouse-polyttool"
      },
      "fieldConfig": {
        "defaults": {
          "color": {
            "mode": "thresholds"
          },
          "custom": {
            "align": "auto",
            "cellOptions": {
              "type": "auto"
            },
            "inspect": false
          },
          "mappings": [],
          "thresholds": {
            "mode": "absolute",
            "steps": [
              {
                "color": "green",
                "value": null
              }
            ]
          }
        },
        "overrides": [
          {
            "matcher": {
              "id": "byName",
              "options": "Strategy"
            },
            "properties": [
              {
                "id": "custom.width",
                "value": 160
              }
            ]
          },
          {
            "matcher": {
              "id": "byName",
              "options": "score"
            },
            "properties": [
              {
                "id": "custom.cellOptions",
                "value": {
                  "mode": "gradient",
                  "type": "gauge"
                }
              },
              {
                "id": "max",
                "value": 1
              },
              {
                "id": "min",
                "value": 0
              },
              {
                "id": "custom.width",
                "value": 150
              }
            ]
          },
          {
            "matcher": {
              "id": "byName",
              "options": "Signal"
            },
            "properties": [
              {
                "id": "custom.cellOptions",
                "value": {
                  "type": "color-background"
                }
              },
              {
                "id": "mappings",
                "value": [
                  {
                    "options": {
                      "SCALPER": {"color": "red", "index": 0, "text": "Scalper"},
                      "SWING": {"color": "yellow", "index": 1, "text": "Swing Trader"},
                      "HOLDER": {"color": "green", "index": 2, "text": "Long-Term Holder"},
                      "DCA_LIKELY": {"color": "blue", "index": 3, "text": "DCA Likely"},
                      "RANDOM": {"color": "semi-dark-orange", "index": 4, "text": "Random Sizing"},
                      "DIVERSIFIED": {"color": "green", "index": 5, "text": "Diversified"},
                      "MODERATE": {"color": "yellow", "index": 6, "text": "Moderate Focus"},
                      "CONCENTRATED": {"color": "red", "index": 7, "text": "Concentrated"},
                      "ARB_LIKELY": {"color": "purple", "index": 8, "text": "Arb Likely"},
                      "NORMAL": {"color": "green", "index": 9, "text": "Normal"},
                      "INSUFFICIENT_DATA": {"color": "gray", "index": 10, "text": "Insufficient Data"},
                      "UNKNOWN": {"color": "gray", "index": 11, "text": "Unknown"},
                      "ERROR": {"color": "dark-red", "index": 12, "text": "Error"}
                    },
                    "type": "value"
                  }
                ]
              },
              {
                "id": "custom.width",
                "value": 150
              }
            ]
          }
        ]
      },
      "gridPos": {
        "h": 7,
        "w": 12,
        "x": 0,
        "y": 13
      },
      "id": 20,
      "options": {
        "cellHeight": "sm",
        "footer": {
          "countRows": false,
          "fields": "",
          "reducer": ["sum"],
          "show": false
        },
        "showHeader": true,
        "sortBy": [
          {
            "desc": false,
            "displayName": "Strategy"
          }
        ]
      },
      "pluginVersion": "11.4.0",
      "targets": [
        {
          "datasource": {
            "type": "grafana-clickhouse-datasource",
            "uid": "clickhouse-polyttool"
          },
          "editorType": "sql",
          "format": 1,
          "queryType": "table",
          "rawSql": "WITH latest_bucket AS (\n  SELECT max(bucket_start) AS b\n  FROM polyttool.detector_results\n  WHERE proxy_wallet = '$proxy_wallet' AND bucket_type = '$bucket_type'\n)\nSELECT\n  multiIf(\n    detector_name = 'HOLDING_STYLE', 'Holding Style',\n    detector_name = 'DCA_LADDERING', 'DCA / Laddering',\n    detector_name = 'MARKET_SELECTION_BIAS', 'Market Concentration',\n    detector_name = 'COMPLETE_SET_ARBISH', 'Complete-Set Arb',\n    detector_name\n  ) AS \"Strategy\",\n  argMax(score, computed_at) AS score,\n  argMax(label, computed_at) AS \"Signal\",\n  any(bucket_start) AS \"As Of\"\nFROM polyttool.detector_results\nWHERE proxy_wallet = '$proxy_wallet'\n  AND bucket_type = '$bucket_type'\n  AND bucket_start = (SELECT b FROM latest_bucket)\nGROUP BY detector_name\nORDER BY detector_name",
          "refId": "A"
        }
      ],
      "title": "Latest Strategy Signals",
      "type": "table"
    },
    {
      "datasource": {
        "type": "grafana-clickhouse-datasource",
        "uid": "clickhouse-polyttool"
      },
      "fieldConfig": {
        "defaults": {
          "color": {
            "mode": "palette-classic"
          },
          "custom": {
            "axisBorderShow": false,
            "axisCenteredZero": false,
            "axisColorMode": "text",
            "axisLabel": "",
            "axisPlacement": "auto",
            "barAlignment": 0,
            "barWidthFactor": 0.6,
            "drawStyle": "line",
            "fillOpacity": 20,
            "gradientMode": "none",
            "hideFrom": {
              "legend": false,
              "tooltip": false,
              "viz": false
            },
            "insertNulls": false,
            "lineInterpolation": "linear",
            "lineWidth": 2,
            "pointSize": 5,
            "scaleDistribution": {
              "type": "linear"
            },
            "showPoints": "auto",
            "spanNulls": false,
            "stacking": {
              "group": "A",
              "mode": "none"
            },
            "thresholdsStyle": {
              "mode": "off"
            }
          },
          "mappings": [],
          "max": 1,
          "min": 0,
          "thresholds": {
            "mode": "absolute",
            "steps": [
              {
                "color": "green",
                "value": null
              }
            ]
          },
          "unit": "percentunit"
        },
        "overrides": []
      },
      "gridPos": {
        "h": 7,
        "w": 12,
        "x": 12,
        "y": 13
      },
      "id": 21,
      "options": {
        "legend": {
          "calcs": ["lastNotNull"],
          "displayMode": "table",
          "placement": "right",
          "showLegend": true
        },
        "tooltip": {
          "mode": "multi",
          "sort": "desc"
        }
      },
      "pluginVersion": "11.4.0",
      "targets": [
        {
          "datasource": {
            "type": "grafana-clickhouse-datasource",
            "uid": "clickhouse-polyttool"
          },
          "editorType": "sql",
          "format": 1,
          "queryType": "timeseries",
          "rawSql": "SELECT\n  bucket_start AS time,\n  multiIf(\n    detector_name = 'HOLDING_STYLE', 'Holding Style',\n    detector_name = 'DCA_LADDERING', 'DCA / Laddering',\n    detector_name = 'MARKET_SELECTION_BIAS', 'Market Concentration',\n    detector_name = 'COMPLETE_SET_ARBISH', 'Complete-Set Arb',\n    detector_name\n  ) AS detector,\n  argMax(score, computed_at) AS score\nFROM polyttool.detector_results\nWHERE proxy_wallet = '$proxy_wallet'\n  AND bucket_type = '$bucket_type'\nGROUP BY bucket_start, detector_name\nORDER BY time",
          "refId": "A"
        }
      ],
      "title": "Strategy Scores Over Time",
      "type": "timeseries"
    },
    {
      "collapsed": false,
      "gridPos": {
        "h": 1,
        "w": 24,
        "x": 0,
        "y": 20
      },
      "id": 103,
      "panels": [],
      "title": "Market Mix & Category Exposure",
      "type": "row"
    },
    {
      "datasource": {
        "type": "grafana-clickhouse-datasource",
        "uid": "clickhouse-polyttool"
      },
      "fieldConfig": {
        "defaults": {
          "color": {
            "mode": "palette-classic"
          },
          "custom": {
            "hideFrom": {
              "legend": false,
              "tooltip": false,
              "viz": false
            }
          },
          "mappings": []
        },
        "overrides": []
      },
      "gridPos": {
        "h": 8,
        "w": 8,
        "x": 0,
        "y": 21
      },
      "id": 30,
      "options": {
        "displayLabels": ["name", "percent"],
        "legend": {
          "displayMode": "table",
          "placement": "right",
          "showLegend": true,
          "values": ["value", "percent"]
        },
        "pieType": "pie",
        "reduceOptions": {
          "calcs": ["lastNotNull"],
          "fields": "",
          "values": false
        },
        "tooltip": {
          "mode": "single",
          "sort": "none"
        }
      },
      "pluginVersion": "11.4.0",
      "targets": [
        {
          "datasource": {
            "type": "grafana-clickhouse-datasource",
            "uid": "clickhouse-polyttool"
          },
          "editorType": "sql",
          "format": 1,
          "queryType": "table",
          "rawSql": "SELECT\n  coalesce(mt.category, 'Unmapped') AS category,\n  sum(t.size * t.price) AS volume\nFROM polyttool.user_trades t\nLEFT JOIN polyttool.market_tokens mt ON t.token_id = mt.token_id\nWHERE t.proxy_wallet = '$proxy_wallet'\nGROUP BY category\nORDER BY volume DESC\nLIMIT 8",
          "refId": "A"
        }
      ],
      "title": "Volume by Category",
      "type": "piechart"
    },
    {
      "datasource": {
        "type": "grafana-clickhouse-datasource",
        "uid": "clickhouse-polyttool"
      },
      "fieldConfig": {
        "defaults": {
          "color": {
            "mode": "thresholds"
          },
          "custom": {
            "align": "auto",
            "cellOptions": {
              "type": "auto"
            },
            "inspect": false
          },
          "mappings": [],
          "thresholds": {
            "mode": "absolute",
            "steps": [
              {
                "color": "green",
                "value": null
              }
            ]
          }
        },
        "overrides": [
          {
            "matcher": {
              "id": "byName",
              "options": "volume"
            },
            "properties": [
              {
                "id": "unit",
                "value": "currencyUSD"
              },
              {
                "id": "decimals",
                "value": 0
              }
            ]
          },
          {
            "matcher": {
              "id": "byName",
              "options": "pct"
            },
            "properties": [
              {
                "id": "unit",
                "value": "percent"
              },
              {
                "id": "decimals",
                "value": 1
              }
            ]
          }
        ]
      },
      "gridPos": {
        "h": 8,
        "w": 8,
        "x": 8,
        "y": 21
      },
      "id": 31,
      "options": {
        "cellHeight": "sm",
        "footer": {
          "countRows": false,
          "fields": "",
          "reducer": ["sum"],
          "show": false
        },
        "showHeader": true,
        "sortBy": [
          {
            "desc": true,
            "displayName": "volume"
          }
        ]
      },
      "pluginVersion": "11.4.0",
      "targets": [
        {
          "datasource": {
            "type": "grafana-clickhouse-datasource",
            "uid": "clickhouse-polyttool"
          },
          "editorType": "sql",
          "format": 1,
          "queryType": "table",
          "rawSql": "WITH totals AS (\n  SELECT sum(size * price) AS total_vol\n  FROM polyttool.user_trades\n  WHERE proxy_wallet = '$proxy_wallet'\n)\nSELECT\n  coalesce(mt.category, 'Unmapped') AS category,\n  sum(t.size * t.price) AS volume,\n  count(DISTINCT t.condition_id) AS markets,\n  sum(t.size * t.price) * 100.0 / (SELECT total_vol FROM totals) AS pct\nFROM polyttool.user_trades t\nLEFT JOIN polyttool.market_tokens mt ON t.token_id = mt.token_id\nWHERE t.proxy_wallet = '$proxy_wallet'\nGROUP BY category\nORDER BY volume DESC\nLIMIT 10",
          "refId": "A"
        }
      ],
      "title": "Top Categories",
      "type": "table"
    },
    {
      "datasource": {
        "type": "grafana-clickhouse-datasource",
        "uid": "clickhouse-polyttool"
      },
      "fieldConfig": {
        "defaults": {
          "color": {
            "mode": "thresholds"
          },
          "custom": {
            "align": "auto",
            "cellOptions": {
              "type": "auto"
            },
            "inspect": false
          },
          "mappings": [],
          "thresholds": {
            "mode": "absolute",
            "steps": [
              {
                "color": "green",
                "value": null
              }
            ]
          }
        },
        "overrides": [
          {
            "matcher": {
              "id": "byName",
              "options": "volume"
            },
            "properties": [
              {
                "id": "unit",
                "value": "currencyUSD"
              },
              {
                "id": "decimals",
                "value": 0
              }
            ]
          }
        ]
      },
      "gridPos": {
        "h": 8,
        "w": 8,
        "x": 16,
        "y": 21
      },
      "id": 32,
      "options": {
        "cellHeight": "sm",
        "footer": {
          "countRows": false,
          "fields": "",
          "reducer": ["sum"],
          "show": false
        },
        "showHeader": true,
        "sortBy": [
          {
            "desc": true,
            "displayName": "volume"
          }
        ]
      },
      "pluginVersion": "11.4.0",
      "targets": [
        {
          "datasource": {
            "type": "grafana-clickhouse-datasource",
            "uid": "clickhouse-polyttool"
          },
          "editorType": "sql",
          "format": 1,
          "queryType": "table",
          "rawSql": "SELECT\n  mt.question AS market,\n  sum(t.size * t.price) AS volume,\n  count() AS trades\nFROM polyttool.user_trades t\nJOIN polyttool.market_tokens mt ON t.token_id = mt.token_id\nWHERE t.proxy_wallet = '$proxy_wallet'\nGROUP BY mt.question\nORDER BY volume DESC\nLIMIT 10",
          "refId": "A"
        }
      ],
      "title": "Top Markets by Volume",
      "type": "table"
    },
    {
      "collapsed": false,
      "gridPos": {
        "h": 1,
        "w": 24,
        "x": 0,
        "y": 29
      },
      "id": 104,
      "panels": [],
      "title": "Liquidity Quality & Arb Feasibility",
      "type": "row"
    },
    {
      "datasource": {
        "type": "grafana-clickhouse-datasource",
        "uid": "clickhouse-polyttool"
      },
      "fieldConfig": {
        "defaults": {
          "color": {
            "mode": "palette-classic"
          },
          "custom": {
            "hideFrom": {
              "legend": false,
              "tooltip": false,
              "viz": false
            }
          },
          "mappings": []
        },
        "overrides": [
          {
            "matcher": {
              "id": "byName",
              "options": "ok"
            },
            "properties": [
              {
                "id": "color",
                "value": {
                  "fixedColor": "green",
                  "mode": "fixed"
                }
              },
              {
                "id": "displayName",
                "value": "OK"
              }
            ]
          },
          {
            "matcher": {
              "id": "byName",
              "options": "no_orderbook"
            },
            "properties": [
              {
                "id": "color",
                "value": {
                  "fixedColor": "gray",
                  "mode": "fixed"
                }
              },
              {
                "id": "displayName",
                "value": "No Orderbook"
              }
            ]
          },
          {
            "matcher": {
              "id": "byName",
              "options": "empty"
            },
            "properties": [
              {
                "id": "color",
                "value": {
                  "fixedColor": "orange",
                  "mode": "fixed"
                }
              },
              {
                "id": "displayName",
                "value": "Empty"
              }
            ]
          },
          {
            "matcher": {
              "id": "byName",
              "options": "one_sided"
            },
            "properties": [
              {
                "id": "color",
                "value": {
                  "fixedColor": "yellow",
                  "mode": "fixed"
                }
              },
              {
                "id": "displayName",
                "value": "One-Sided"
              }
            ]
          },
          {
            "matcher": {
              "id": "byName",
              "options": "error"
            },
            "properties": [
              {
                "id": "color",
                "value": {
                  "fixedColor": "red",
                  "mode": "fixed"
                }
              },
              {
                "id": "displayName",
                "value": "Error"
              }
            ]
          }
        ]
      },
      "gridPos": {
        "h": 7,
        "w": 6,
        "x": 0,
        "y": 30
      },
      "id": 40,
      "options": {
        "displayLabels": ["name", "percent"],
        "legend": {
          "displayMode": "table",
          "placement": "bottom",
          "showLegend": true,
          "values": ["value"]
        },
        "pieType": "pie",
        "reduceOptions": {
          "calcs": ["lastNotNull"],
          "fields": "",
          "values": false
        },
        "tooltip": {
          "mode": "single",
          "sort": "none"
        }
      },
      "pluginVersion": "11.4.0",
      "targets": [
        {
          "datasource": {
            "type": "grafana-clickhouse-datasource",
            "uid": "clickhouse-polyttool"
          },
          "editorType": "sql",
          "format": 1,
          "queryType": "table",
          "rawSql": "SELECT\n  countIf(status = 'ok') AS ok,\n  countIf(status = 'no_orderbook') AS no_orderbook,\n  countIf(status = 'empty') AS empty,\n  countIf(status = 'one_sided') AS one_sided,\n  countIf(status = 'error') AS error\nFROM polyttool.token_orderbook_snapshots\nWHERE $__timeFilter(snapshot_ts)",
          "refId": "A"
        }
      ],
      "title": "Orderbook Quality",
      "type": "piechart"
    },
    {
      "datasource": {
        "type": "grafana-clickhouse-datasource",
        "uid": "clickhouse-polyttool"
      },
      "fieldConfig": {
        "defaults": {
          "color": {
            "mode": "palette-classic"
          },
          "custom": {
            "axisBorderShow": false,
            "axisCenteredZero": false,
            "axisColorMode": "text",
            "axisLabel": "OK %",
            "axisPlacement": "auto",
            "barAlignment": 0,
            "barWidthFactor": 0.6,
            "drawStyle": "line",
            "fillOpacity": 20,
            "gradientMode": "none",
            "hideFrom": {
              "legend": false,
              "tooltip": false,
              "viz": false
            },
            "insertNulls": false,
            "lineInterpolation": "linear",
            "lineWidth": 2,
            "pointSize": 5,
            "scaleDistribution": {
              "type": "linear"
            },
            "showPoints": "auto",
            "spanNulls": false,
            "stacking": {
              "group": "A",
              "mode": "none"
            },
            "thresholdsStyle": {
              "mode": "off"
            }
          },
          "mappings": [],
          "max": 100,
          "min": 0,
          "thresholds": {
            "mode": "absolute",
            "steps": [
              {
                "color": "green",
                "value": null
              }
            ]
          },
          "unit": "percent"
        },
        "overrides": []
      },
      "gridPos": {
        "h": 7,
        "w": 6,
        "x": 6,
        "y": 30
      },
      "id": 41,
      "options": {
        "legend": {
          "calcs": ["mean"],
          "displayMode": "list",
          "placement": "bottom",
          "showLegend": true
        },
        "tooltip": {
          "mode": "single",
          "sort": "none"
        }
      },
      "pluginVersion": "11.4.0",
      "targets": [
        {
          "datasource": {
            "type": "grafana-clickhouse-datasource",
            "uid": "clickhouse-polyttool"
          },
          "editorType": "sql",
          "format": 1,
          "queryType": "timeseries",
          "rawSql": "SELECT\n  toStartOfDay(snapshot_ts) AS time,\n  countIf(status = 'ok') * 100.0 / count() AS \"OK Rate\"\nFROM polyttool.token_orderbook_snapshots\nWHERE $__timeFilter(snapshot_ts)\nGROUP BY time\nORDER BY time",
          "refId": "A"
        }
      ],
      "title": "Orderbook OK Rate Over Time",
      "type": "timeseries"
    },
    {
      "datasource": {
        "type": "grafana-clickhouse-datasource",
        "uid": "clickhouse-polyttool"
      },
      "fieldConfig": {
        "defaults": {
          "color": {
            "mode": "thresholds"
          },
          "mappings": [],
          "thresholds": {
            "mode": "absolute",
            "steps": [
              {
                "color": "green",
                "value": null
              }
            ]
          }
        },
        "overrides": []
      },
      "gridPos": {
        "h": 3,
        "w": 4,
        "x": 12,
        "y": 30
      },
      "id": 50,
      "options": {
        "colorMode": "value",
        "graphMode": "none",
        "justifyMode": "auto",
        "orientation": "auto",
        "reduceOptions": {
          "calcs": ["lastNotNull"],
          "fields": "",
          "values": false
        },
        "textMode": "auto",
        "wideLayout": true
      },
      "pluginVersion": "11.4.0",
      "targets": [
        {
          "datasource": {
            "type": "grafana-clickhouse-datasource",
            "uid": "clickhouse-polyttool"
          },
          "editorType": "sql",
          "format": 1,
          "queryType": "table",
          "rawSql": "SELECT count(DISTINCT condition_id) AS arb_events\nFROM polyttool.arb_feasibility_bucket\nWHERE proxy_wallet = '$proxy_wallet'\n  AND bucket_type = '$bucket_type'",
          "refId": "A"
        }
      ],
      "title": "Arb Events",
      "type": "stat"
    },
    {
      "datasource": {
        "type": "grafana-clickhouse-datasource",
        "uid": "clickhouse-polyttool"
      },
      "fieldConfig": {
        "defaults": {
          "color": {
            "mode": "thresholds"
          },
          "mappings": [],
          "thresholds": {
            "mode": "absolute",
            "steps": [
              {
                "color": "blue",
                "value": null
              }
            ]
          },
          "unit": "currencyUSD"
        },
        "overrides": []
      },
      "gridPos": {
        "h": 3,
        "w": 4,
        "x": 16,
        "y": 30
      },
      "id": 51,
      "options": {
        "colorMode": "value",
        "graphMode": "none",
        "justifyMode": "auto",
        "orientation": "auto",
        "reduceOptions": {
          "calcs": ["sum"],
          "fields": "",
          "values": false
        },
        "textMode": "auto",
        "wideLayout": true
      },
      "pluginVersion": "11.4.0",
      "targets": [
        {
          "datasource": {
            "type": "grafana-clickhouse-datasource",
            "uid": "clickhouse-polyttool"
          },
          "editorType": "sql",
          "format": 1,
          "queryType": "table",
          "rawSql": "SELECT sum(fees) AS total_fees\nFROM (\n  SELECT argMax(total_fees_est_usdc, computed_at) AS fees\n  FROM polyttool.arb_feasibility_bucket\n  WHERE proxy_wallet = '$proxy_wallet'\n    AND bucket_type = '$bucket_type'\n  GROUP BY condition_id\n)",
          "refId": "A"
        }
      ],
      "title": "Total Fees Est",
      "type": "stat"
    },
    {
      "datasource": {
        "type": "grafana-clickhouse-datasource",
        "uid": "clickhouse-polyttool"
      },
      "fieldConfig": {
        "defaults": {
          "color": {
            "mode": "thresholds"
          },
          "mappings": [],
          "thresholds": {
            "mode": "absolute",
            "steps": [
              {
                "color": "orange",
                "value": null
              }
            ]
          },
          "unit": "currencyUSD"
        },
        "overrides": []
      },
      "gridPos": {
        "h": 3,
        "w": 4,
        "x": 20,
        "y": 30
      },
      "id": 52,
      "options": {
        "colorMode": "value",
        "graphMode": "none",
        "justifyMode": "auto",
        "orientation": "auto",
        "reduceOptions": {
          "calcs": ["sum"],
          "fields": "",
          "values": false
        },
        "textMode": "auto",
        "wideLayout": true
      },
      "pluginVersion": "11.4.0",
      "targets": [
        {
          "datasource": {
            "type": "grafana-clickhouse-datasource",
            "uid": "clickhouse-polyttool"
          },
          "editorType": "sql",
          "format": 1,
          "queryType": "table",
          "rawSql": "SELECT sum(slippage) AS total_slippage\nFROM (\n  SELECT argMax(total_slippage_est_usdc, computed_at) AS slippage\n  FROM polyttool.arb_feasibility_bucket\n  WHERE proxy_wallet = '$proxy_wallet'\n    AND bucket_type = '$bucket_type'\n  GROUP BY condition_id\n)",
          "refId": "A"
        }
      ],
      "title": "Total Slippage Est",
      "type": "stat"
    },
    {
      "datasource": {
        "type": "grafana-clickhouse-datasource",
        "uid": "clickhouse-polyttool"
      },
      "fieldConfig": {
        "defaults": {
          "color": {
            "mode": "palette-classic"
          },
          "custom": {
            "hideFrom": {
              "legend": false,
              "tooltip": false,
              "viz": false
            }
          },
          "mappings": []
        },
        "overrides": [
          {
            "matcher": {
              "id": "byName",
              "options": "high"
            },
            "properties": [
              {
                "id": "color",
                "value": {
                  "fixedColor": "green",
                  "mode": "fixed"
                }
              },
              {
                "id": "displayName",
                "value": "High"
              }
            ]
          },
          {
            "matcher": {
              "id": "byName",
              "options": "medium"
            },
            "properties": [
              {
                "id": "color",
                "value": {
                  "fixedColor": "yellow",
                  "mode": "fixed"
                }
              },
              {
                "id": "displayName",
                "value": "Medium"
              }
            ]
          },
          {
            "matcher": {
              "id": "byName",
              "options": "low"
            },
            "properties": [
              {
                "id": "color",
                "value": {
                  "fixedColor": "red",
                  "mode": "fixed"
                }
              },
              {
                "id": "displayName",
                "value": "Low"
              }
            ]
          }
        ]
      },
      "gridPos": {
        "h": 4,
        "w": 12,
        "x": 12,
        "y": 33
      },
      "id": 53,
      "options": {
        "displayLabels": ["name", "value"],
        "legend": {
          "displayMode": "table",
          "placement": "right",
          "showLegend": true,
          "values": ["value", "percent"]
        },
        "pieType": "pie",
        "reduceOptions": {
          "calcs": ["lastNotNull"],
          "fields": "",
          "values": false
        },
        "tooltip": {
          "mode": "single",
          "sort": "none"
        }
      },
      "pluginVersion": "11.4.0",
      "targets": [
        {
          "datasource": {
            "type": "grafana-clickhouse-datasource",
            "uid": "clickhouse-polyttool"
          },
          "editorType": "sql",
          "format": 1,
          "queryType": "table",
          "rawSql": "SELECT\n  countIf(confidence = 'high') AS high,\n  countIf(confidence = 'medium') AS medium,\n  countIf(confidence = 'low') AS low\nFROM (\n  SELECT argMax(confidence, computed_at) AS confidence\n  FROM polyttool.arb_feasibility_bucket\n  WHERE proxy_wallet = '$proxy_wallet'\n    AND bucket_type = '$bucket_type'\n  GROUP BY condition_id\n)",
          "refId": "A"
        }
      ],
      "title": "Arb Confidence Distribution",
      "type": "piechart"
    }
  ],
  "refresh": "30s",
  "schemaVersion": 39,
  "tags": [
    "polyttool",
    "overview"
  ],
  "templating": {
    "list": [
      {
        "current": {},
        "datasource": {
          "type": "grafana-clickhouse-datasource",
          "uid": "clickhouse-polyttool"
        },
        "definition": "SELECT proxy_wallet AS __value, coalesce(username, proxy_wallet) AS __text\nFROM polyttool.users\nORDER BY last_updated DESC",
        "hide": 0,
        "includeAll": false,
        "label": "User",
        "multi": false,
        "name": "proxy_wallet",
        "options": [],
        "query": "SELECT proxy_wallet AS __value, coalesce(username, proxy_wallet) AS __text\nFROM polyttool.users\nORDER BY last_updated DESC",
        "refresh": 2,
        "regex": "",
        "skipUrlSync": false,
        "sort": 0,
        "type": "query"
      },
      {
        "current": {
          "selected": true,
          "text": "day",
          "value": "day"
        },
        "hide": 0,
        "includeAll": false,
        "label": "Time Bucket",
        "multi": false,
        "name": "bucket_type",
        "options": [
          {
            "selected": true,
            "text": "day",
            "value": "day"
          },
          {
            "selected": false,
            "text": "hour",
            "value": "hour"
          },
          {
            "selected": false,
            "text": "week",
            "value": "week"
          }
        ],
        "query": "day,hour,week",
        "queryValue": "",
        "skipUrlSync": false,
        "type": "custom"
      }
    ]
  },
  "time": {
    "from": "now-30d",
    "to": "now"
  },
  "timepicker": {},
  "timezone": "browser",
  "title": "PolyTool - User Overview",
  "uid": "polyttool-user-overview",
  "version": 1,
  "weekStart": ""
}
